easestress/__init__.py
easestress/main.py
easestress-0.9.dist-info/METADATA
easestress-0.9.dist-info/WHEEL
easestress-0.9.dist-info/RECORD
